rerun_loader_mjcf/__init__.py
rerun_loader_mjcf-1.0.1.dist-info/WHEEL
rerun_loader_mjcf-1.0.1.dist-info/entry_points.txt
rerun_loader_mjcf-1.0.1.dist-info/METADATA
rerun_loader_mjcf-1.0.1.dist-info/RECORD
