Metadata-Version: 2.3
Name: rerun-loader-mjcf
Version: 1.0.1
Summary: A Rerun data loader for MJCF (MuJoCo XML) files
Author: Jafar Uruc
Author-email: Jafar Uruc <jafar@reimaginerobotics.ai>
License: MIT License
Classifier: Development Status :: 4 - Beta
Classifier: Intended Audience :: Developers
Classifier: Programming Language :: Python :: 3
Classifier: Programming Language :: Python :: 3.10
Classifier: Programming Language :: Python :: 3.11
Classifier: Programming Language :: Python :: 3.12
Classifier: Programming Language :: Python :: 3.13
Classifier: Topic :: Software Development :: Libraries :: Python Modules
Requires-Dist: mujoco>=3.3.0
Requires-Dist: numpy>=2
Requires-Dist: rerun-sdk>=0.29
Requires-Python: >=3.10
Project-URL: Homepage, https://github.com/reimagine-Robotics/rerun-loader-mjcf
Project-URL: Issues, https://github.com/reimagine-Robotics/rerun-loader-mjcf/issues
Project-URL: Repository, https://github.com/reimagine-Robotics/rerun-loader-mjcf
